mcp_ntopng/.env.example
mcp_ntopng/__init__.py
mcp_ntopng/main.py
mcp_ntopng/mcp_config.py
mcp_ntopng/mcp_server.py
mcp_ntopng/ntopng_schema.py
mcp_ntopng-0.1.1.dist-info/METADATA
mcp_ntopng-0.1.1.dist-info/WHEEL
mcp_ntopng-0.1.1.dist-info/entry_points.txt
mcp_ntopng-0.1.1.dist-info/licenses/LICENSE
mcp_ntopng-0.1.1.dist-info/RECORD
