Metadata-Version: 2.4
Name: mcp-ntopng
Version: 0.1.1
Summary: An MCP Server for ntopng integration
Author: Graziano Labs Corp.
Maintainer-email: Marco Graziano <marco@graziano.com>
License: MIT
License-File: LICENSE
Keywords: cybersecurity,llm,mcp,ntop
Classifier: Development Status :: 4 - Beta
Classifier: Intended Audience :: Information Technology
Classifier: License :: OSI Approved :: MIT License
Classifier: Programming Language :: Python :: 3
Classifier: Programming Language :: Python :: 3.13
Requires-Python: >=3.13
Requires-Dist: clickhouse-driver>=0.2.5
Requires-Dist: mcp[cli]>=1.3.0
Requires-Dist: pip-system-certs>=4.0
Requires-Dist: python-dotenv>=1.0.1
Requires-Dist: requests>=2.32.3
